[
    {
        "name": "cb de 53",
        "initial": {
            "pc": 39274,
            "s": 146,
            "a": 214,
            "x": 173,
            "y": 197,
            "p": 101,
            "ram": [
                [39274, 203],
                [39275, 222],
                [39276, 83]
            ]
        },
        "final": {
            "pc": 39276,
            "s": 146,
            "a": 214,
            "x": 166,
            "y": 197,
            "p": 228,
            "ram": [
                [39274, 203],
                [39275, 222],
                [39276, 83]
            ]
        },
        "cycles": [
            [39274, 203, "read"],
            [39275, 222, "read"]
        ]
    },
    {
        "name": "cb 78 78",
        "initial": {
            "pc": 4727,
            "s": 69,
            "a": 39,
            "x": 3,
            "y": 181,
            "p": 33,
            "ram": [
                [4727, 203],
                [4728, 120],
                [4729, 120]
            ]
        },
        "final": {
            "pc": 4729,
            "s": 69,
            "a": 39,
            "x": 139,
            "y": 181,
            "p": 160,
            "ram": [
                [4727, 203],
                [4728, 120],
                [4729, 120]
            ]
        },
        "cycles": [
            [4727, 203, "read"],
            [4728, 120, "read"]
        ]
    },
    {
        "name": "cb 7e fa",
        "initial": {
            "pc": 7395,
            "s": 93,
            "a": 165,
            "x": 108,
            "y": 211,
            "p": 98,
            "ram": [
                [7395, 203],
                [7396, 126],
                [7397, 250]
            ]
        },
        "final": {
            "pc": 7397,
            "s": 93,
            "a": 165,
            "x": 166,
            "y": 211,
            "p": 224,
            "ram": [
                [7395, 203],
                [7396, 126],
                [7397, 250]
            ]
        },
        "cycles": [
            [7395, 203, "read"],
            [7396, 126, "read"]
        ]
    },
    {
        "name": "cb c8 7f",
        "initial": {
            "pc": 17704,
            "s": 138,
            "a": 98,
            "x": 140,
            "y": 124,
            "p": 38,
            "ram": [
                [17704, 203],
                [17705, 200],
                [17706, 127]
            ]
        },
        "final": {
            "pc": 17706,
            "s": 138,
            "a": 98,
            "x": 56,
            "y": 124,
            "p": 36,
            "ram": [
                [17704, 203],
                [17705, 200],
                [17706, 127]
            ]
        },
        "cycles": [
            [17704, 203, "read"],
            [17705, 200, "read"]
        ]
    },
    {
        "name": "cb f5 06",
        "initial": {
            "pc": 12075,
            "s": 18,
            "a": 157,
            "x": 118,
            "y": 251,
            "p": 168,
            "ram": [
                [12075, 203],
                [12076, 245],
                [12077, 6]
            ]
        },
        "final": {
            "pc": 12077,
            "s": 18,
            "a": 157,
            "x": 31,
            "y": 251,
            "p": 40,
            "ram": [
                [12075, 203],
                [12076, 245],
                [12077, 6]
            ]
        },
        "cycles": [
            [12075, 203, "read"],
            [12076, 245, "read"]
        ]
    },
    {
        "name": "cb 84 5e",
        "initial": {
            "pc": 19398,
            "s": 1,
            "a": 77,
            "x": 210,
            "y": 49,
            "p": 96,
            "ram": [
                [19398, 203],
                [19399, 132],
                [19400, 94]
            ]
        },
        "final": {
            "pc": 19400,
            "s": 1,
            "a": 77,
            "x": 188,
            "y": 49,
            "p": 224,
            "ram": [
                [19398, 203],
                [19399, 132],
                [19400, 94]
            ]
        },
        "cycles": [
            [19398, 203, "read"],
            [19399, 132, "read"]
        ]
    },
    {
        "name": "cb 86 de",
        "initial": {
            "pc": 13747,
            "s": 126,
            "a": 144,
            "x": 163,
            "y": 74,
            "p": 235,
            "ram": [
                [13747, 203],
                [13748, 134],
                [13749, 222]
            ]
        },
        "final": {
            "pc": 13749,
            "s": 126,
            "a": 144,
            "x": 250,
            "y": 74,
            "p": 232,
            "ram": [
                [13747, 203],
                [13748, 134],
                [13749, 222]
            ]
        },
        "cycles": [
            [13747, 203, "read"],
            [13748, 134, "read"]
        ]
    },
    {
        "name": "cb e9 05",
        "initial": {
            "pc": 45413,
            "s": 74,
            "a": 36,
            "x": 41,
            "y": 171,
            "p": 97,
            "ram": [
                [45413, 203],
                [45414, 233],
                [45415, 5]
            ]
        },
        "final": {
            "pc": 45415,
            "s": 74,
            "a": 36,
            "x": 55,
            "y": 171,
            "p": 96,
            "ram": [
                [45413, 203],
                [45414, 233],
                [45415, 5]
            ]
        },
        "cycles": [
            [45413, 203, "read"],
            [45414, 233, "read"]
        ]
    },
    {
        "name": "cb 16 b5",
        "initial": {
            "pc": 54444,
            "s": 213,
            "a": 70,
            "x": 88,
            "y": 178,
            "p": 233,
            "ram": [
                [54444, 203],
                [54445, 22],
                [54446, 181]
            ]
        },
        "final": {
            "pc": 54446,
            "s": 213,
            "a": 70,
            "x": 42,
            "y": 178,
            "p": 105,
            "ram": [
                [54444, 203],
                [54445, 22],
                [54446, 181]
            ]
        },
        "cycles": [
            [54444, 203, "read"],
            [54445, 22, "read"]
        ]
    },
    {
        "name": "cb 7c b9",
        "initial": {
            "pc": 54568,
            "s": 251,
            "a": 186,
            "x": 75,
            "y": 22,
            "p": 96,
            "ram": [
                [54568, 203],
                [54569, 124],
                [54570, 185]
            ]
        },
        "final": {
            "pc": 54570,
            "s": 251,
            "a": 186,
            "x": 142,
            "y": 22,
            "p": 224,
            "ram": [
                [54568, 203],
                [54569, 124],
                [54570, 185]
            ]
        },
        "cycles": [
            [54568, 203, "read"],
            [54569, 124, "read"]
        ]
    },
    {
        "name": "cb 07 d6",
        "initial": {
            "pc": 37489,
            "s": 227,
            "a": 37,
            "x": 66,
            "y": 59,
            "p": 164,
            "ram": [
                [37489, 203],
                [37490, 7],
                [37491, 214]
            ]
        },
        "final": {
            "pc": 37491,
            "s": 227,
            "a": 37,
            "x": 249,
            "y": 59,
            "p": 164,
            "ram": [
                [37489, 203],
                [37490, 7],
                [37491, 214]
            ]
        },
        "cycles": [
            [37489, 203, "read"],
            [37490, 7, "read"]
        ]
    },
    {
        "name": "cb 33 c5",
        "initial": {
            "pc": 23930,
            "s": 50,
            "a": 92,
            "x": 251,
            "y": 89,
            "p": 225,
            "ram": [
                [23930, 203],
                [23931, 51],
                [23932, 197]
            ]
        },
        "final": {
            "pc": 23932,
            "s": 50,
            "a": 92,
            "x": 37,
            "y": 89,
            "p": 97,
            "ram": [
                [23930, 203],
                [23931, 51],
                [23932, 197]
            ]
        },
        "cycles": [
            [23930, 203, "read"],
            [23931, 51, "read"]
        ]
    },
    {
        "name": "cb f6 d2",
        "initial": {
            "pc": 43195,
            "s": 19,
            "a": 106,
            "x": 22,
            "y": 116,
            "p": 237,
            "ram": [
                [43195, 203],
                [43196, 246],
                [43197, 210]
            ]
        },
        "final": {
            "pc": 43197,
            "s": 19,
            "a": 106,
            "x": 12,
            "y": 116,
            "p": 108,
            "ram": [
                [43195, 203],
                [43196, 246],
                [43197, 210]
            ]
        },
        "cycles": [
            [43195, 203, "read"],
            [43196, 246, "read"]
        ]
    },
    {
        "name": "cb c3 12",
        "initial": {
            "pc": 52096,
            "s": 71,
            "a": 165,
            "x": 131,
            "y": 229,
            "p": 108,
            "ram": [
                [52096, 203],
                [52097, 195],
                [52098, 18]
            ]
        },
        "final": {
            "pc": 52098,
            "s": 71,
            "a": 165,
            "x": 190,
            "y": 229,
            "p": 236,
            "ram": [
                [52096, 203],
                [52097, 195],
                [52098, 18]
            ]
        },
        "cycles": [
            [52096, 203, "read"],
            [52097, 195, "read"]
        ]
    },
    {
        "name": "cb 86 ae",
        "initial": {
            "pc": 3517,
            "s": 104,
            "a": 45,
            "x": 149,
            "y": 228,
            "p": 163,
            "ram": [
                [3517, 203],
                [3518, 134],
                [3519, 174]
            ]
        },
        "final": {
            "pc": 3519,
            "s": 104,
            "a": 45,
            "x": 127,
            "y": 228,
            "p": 32,
            "ram": [
                [3517, 203],
                [3518, 134],
                [3519, 174]
            ]
        },
        "cycles": [
            [3517, 203, "read"],
            [3518, 134, "read"]
        ]
    },
    {
        "name": "cb 5c 8f",
        "initial": {
            "pc": 62478,
            "s": 192,
            "a": 168,
            "x": 120,
            "y": 218,
            "p": 32,
            "ram": [
                [62478, 203],
                [62479, 92],
                [62480, 143]
            ]
        },
        "final": {
            "pc": 62480,
            "s": 192,
            "a": 168,
            "x": 204,
            "y": 218,
            "p": 160,
            "ram": [
                [62478, 203],
                [62479, 92],
                [62480, 143]
            ]
        },
        "cycles": [
            [62478, 203, "read"],
            [62479, 92, "read"]
        ]
    },
    {
        "name": "cb 04 90",
        "initial": {
            "pc": 27688,
            "s": 182,
            "a": 165,
            "x": 149,
            "y": 254,
            "p": 37,
            "ram": [
                [27688, 203],
                [27689, 4],
                [27690, 144]
            ]
        },
        "final": {
            "pc": 27690,
            "s": 182,
            "a": 165,
            "x": 129,
            "y": 254,
            "p": 165,
            "ram": [
                [27688, 203],
                [27689, 4],
                [27690, 144]
            ]
        },
        "cycles": [
            [27688, 203, "read"],
            [27689, 4, "read"]
        ]
    },
    {
        "name": "cb 46 df",
        "initial": {
            "pc": 9594,
            "s": 46,
            "a": 127,
            "x": 62,
            "y": 70,
            "p": 232,
            "ram": [
                [9594, 203],
                [9595, 70],
                [9596, 223]
            ]
        },
        "final": {
            "pc": 9596,
            "s": 46,
            "a": 127,
            "x": 248,
            "y": 70,
            "p": 232,
            "ram": [
                [9594, 203],
                [9595, 70],
                [9596, 223]
            ]
        },
        "cycles": [
            [9594, 203, "read"],
            [9595, 70, "read"]
        ]
    },
    {
        "name": "cb b3 f1",
        "initial": {
            "pc": 8171,
            "s": 15,
            "a": 197,
            "x": 64,
            "y": 28,
            "p": 236,
            "ram": [
                [8171, 203],
                [8172, 179],
                [8173, 241]
            ]
        },
        "final": {
            "pc": 8173,
            "s": 15,
            "a": 197,
            "x": 141,
            "y": 28,
            "p": 236,
            "ram": [
                [8171, 203],
                [8172, 179],
                [8173, 241]
            ]
        },
        "cycles": [
            [8171, 203, "read"],
            [8172, 179, "read"]
        ]
    },
    {
        "name": "cb f3 a9",
        "initial": {
            "pc": 7576,
            "s": 164,
            "a": 117,
            "x": 152,
            "y": 120,
            "p": 97,
            "ram": [
                [7576, 203],
                [7577, 243],
                [7578, 169]
            ]
        },
        "final": {
            "pc": 7578,
            "s": 164,
            "a": 117,
            "x": 29,
            "y": 120,
            "p": 96,
            "ram": [
                [7576, 203],
                [7577, 243],
                [7578, 169]
            ]
        },
        "cycles": [
            [7576, 203, "read"],
            [7577, 243, "read"]
        ]
    },
    {
        "name": "cb 42 c4",
        "initial": {
            "pc": 22658,
            "s": 20,
            "a": 62,
            "x": 82,
            "y": 74,
            "p": 110,
            "ram": [
                [22658, 203],
                [22659, 66],
                [22660, 196]
            ]
        },
        "final": {
            "pc": 22660,
            "s": 20,
            "a": 62,
            "x": 208,
            "y": 74,
            "p": 236,
            "ram": [
                [22658, 203],
                [22659, 66],
                [22660, 196]
            ]
        },
        "cycles": [
            [22658, 203, "read"],
            [22659, 66, "read"]
        ]
    },
    {
        "name": "cb 83 3d",
        "initial": {
            "pc": 2073,
            "s": 63,
            "a": 109,
            "x": 15,
            "y": 226,
            "p": 166,
            "ram": [
                [2073, 203],
                [2074, 131],
                [2075, 61]
            ]
        },
        "final": {
            "pc": 2075,
            "s": 63,
            "a": 109,
            "x": 138,
            "y": 226,
            "p": 164,
            "ram": [
                [2073, 203],
                [2074, 131],
                [2075, 61]
            ]
        },
        "cycles": [
            [2073, 203, "read"],
            [2074, 131, "read"]
        ]
    },
    {
        "name": "cb 7f f4",
        "initial": {
            "pc": 39857,
            "s": 192,
            "a": 169,
            "x": 200,
            "y": 107,
            "p": 39,
            "ram": [
                [39857, 203],
                [39858, 127],
                [39859, 244]
            ]
        },
        "final": {
            "pc": 39859,
            "s": 192,
            "a": 169,
            "x": 9,
            "y": 107,
            "p": 37,
            "ram": [
                [39857, 203],
                [39858, 127],
                [39859, 244]
            ]
        },
        "cycles": [
            [39857, 203, "read"],
            [39858, 127, "read"]
        ]
    },
    {
        "name": "cb 5b 25",
        "initial": {
            "pc": 32388,
            "s": 99,
            "a": 98,
            "x": 181,
            "y": 234,
            "p": 39,
            "ram": [
                [32388, 203],
                [32389, 91],
                [32390, 37]
            ]
        },
        "final": {
            "pc": 32390,
            "s": 99,
            "a": 98,
            "x": 197,
            "y": 234,
            "p": 164,
            "ram": [
                [32388, 203],
                [32389, 91],
                [32390, 37]
            ]
        },
        "cycles": [
            [32388, 203, "read"],
            [32389, 91, "read"]
        ]
    },
    {
        "name": "cb 81 e5",
        "initial": {
            "pc": 60458,
            "s": 131,
            "a": 95,
            "x": 219,
            "y": 127,
            "p": 45,
            "ram": [
                [60458, 203],
                [60459, 129],
                [60460, 229]
            ]
        },
        "final": {
            "pc": 60460,
            "s": 131,
            "a": 95,
            "x": 218,
            "y": 127,
            "p": 172,
            "ram": [
                [60458, 203],
                [60459, 129],
                [60460, 229]
            ]
        },
        "cycles": [
            [60458, 203, "read"],
            [60459, 129, "read"]
        ]
    },
    {
        "name": "cb c5 e7",
        "initial": {
            "pc": 49352,
            "s": 198,
            "a": 52,
            "x": 98,
            "y": 141,
            "p": 46,
            "ram": [
                [49352, 203],
                [49353, 197],
                [49354, 231]
            ]
        },
        "final": {
            "pc": 49354,
            "s": 198,
            "a": 52,
            "x": 91,
            "y": 141,
            "p": 44,
            "ram": [
                [49352, 203],
                [49353, 197],
                [49354, 231]
            ]
        },
        "cycles": [
            [49352, 203, "read"],
            [49353, 197, "read"]
        ]
    },
    {
        "name": "cb 60 3d",
        "initial": {
            "pc": 4227,
            "s": 195,
            "a": 239,
            "x": 143,
            "y": 98,
            "p": 41,
            "ram": [
                [4227, 203],
                [4228, 96],
                [4229, 61]
            ]
        },
        "final": {
            "pc": 4229,
            "s": 195,
            "a": 239,
            "x": 47,
            "y": 98,
            "p": 41,
            "ram": [
                [4227, 203],
                [4228, 96],
                [4229, 61]
            ]
        },
        "cycles": [
            [4227, 203, "read"],
            [4228, 96, "read"]
        ]
    },
    {
        "name": "cb 14 1a",
        "initial": {
            "pc": 29578,
            "s": 119,
            "a": 97,
            "x": 143,
            "y": 50,
            "p": 168,
            "ram": [
                [29578, 203],
                [29579, 20],
                [29580, 26]
            ]
        },
        "final": {
            "pc": 29580,
            "s": 119,
            "a": 97,
            "x": 237,
            "y": 50,
            "p": 168,
            "ram": [
                [29578, 203],
                [29579, 20],
                [29580, 26]
            ]
        },
        "cycles": [
            [29578, 203, "read"],
            [29579, 20, "read"]
        ]
    },
    {
        "name": "cb 37 4b",
        "initial": {
            "pc": 17974,
            "s": 6,
            "a": 162,
            "x": 204,
            "y": 174,
            "p": 235,
            "ram": [
                [17974, 203],
                [17975, 55],
                [17976, 75]
            ]
        },
        "final": {
            "pc": 17976,
            "s": 6,
            "a": 162,
            "x": 73,
            "y": 174,
            "p": 105,
            "ram": [
                [17974, 203],
                [17975, 55],
                [17976, 75]
            ]
        },
        "cycles": [
            [17974, 203, "read"],
            [17975, 55, "read"]
        ]
    },
    {
        "name": "cb 7b 8c",
        "initial": {
            "pc": 7985,
            "s": 175,
            "a": 11,
            "x": 212,
            "y": 153,
            "p": 172,
            "ram": [
                [7985, 203],
                [7986, 123],
                [7987, 140]
            ]
        },
        "final": {
            "pc": 7987,
            "s": 175,
            "a": 11,
            "x": 133,
            "y": 153,
            "p": 172,
            "ram": [
                [7985, 203],
                [7986, 123],
                [7987, 140]
            ]
        },
        "cycles": [
            [7985, 203, "read"],
            [7986, 123, "read"]
        ]
    },
    {
        "name": "cb 8e 60",
        "initial": {
            "pc": 45938,
            "s": 60,
            "a": 196,
            "x": 12,
            "y": 1,
            "p": 102,
            "ram": [
                [45938, 203],
                [45939, 142],
                [45940, 96]
            ]
        },
        "final": {
            "pc": 45940,
            "s": 60,
            "a": 196,
            "x": 118,
            "y": 1,
            "p": 100,
            "ram": [
                [45938, 203],
                [45939, 142],
                [45940, 96]
            ]
        },
        "cycles": [
            [45938, 203, "read"],
            [45939, 142, "read"]
        ]
    },
    {
        "name": "cb 27 bb",
        "initial": {
            "pc": 17070,
            "s": 240,
            "a": 75,
            "x": 19,
            "y": 91,
            "p": 239,
            "ram": [
                [17070, 203],
                [17071, 39],
                [17072, 187]
            ]
        },
        "final": {
            "pc": 17072,
            "s": 240,
            "a": 75,
            "x": 220,
            "y": 91,
            "p": 236,
            "ram": [
                [17070, 203],
                [17071, 39],
                [17072, 187]
            ]
        },
        "cycles": [
            [17070, 203, "read"],
            [17071, 39, "read"]
        ]
    },
    {
        "name": "cb 58 c6",
        "initial": {
            "pc": 4337,
            "s": 249,
            "a": 246,
            "x": 11,
            "y": 65,
            "p": 37,
            "ram": [
                [4337, 203],
                [4338, 88],
                [4339, 198]
            ]
        },
        "final": {
            "pc": 4339,
            "s": 249,
            "a": 246,
            "x": 170,
            "y": 65,
            "p": 164,
            "ram": [
                [4337, 203],
                [4338, 88],
                [4339, 198]
            ]
        },
        "cycles": [
            [4337, 203, "read"],
            [4338, 88, "read"]
        ]
    },
    {
        "name": "cb 63 a3",
        "initial": {
            "pc": 39155,
            "s": 167,
            "a": 34,
            "x": 231,
            "y": 167,
            "p": 38,
            "ram": [
                [39155, 203],
                [39156, 99],
                [39157, 163]
            ]
        },
        "final": {
            "pc": 39157,
            "s": 167,
            "a": 34,
            "x": 191,
            "y": 167,
            "p": 164,
            "ram": [
                [39155, 203],
                [39156, 99],
                [39157, 163]
            ]
        },
        "cycles": [
            [39155, 203, "read"],
            [39156, 99, "read"]
        ]
    },
    {
        "name": "cb a1 9b",
        "initial": {
            "pc": 65238,
            "s": 35,
            "a": 190,
            "x": 114,
            "y": 234,
            "p": 237,
            "ram": [
                [65238, 203],
                [65239, 161],
                [65240, 155]
            ]
        },
        "final": {
            "pc": 65240,
            "s": 35,
            "a": 190,
            "x": 145,
            "y": 234,
            "p": 236,
            "ram": [
                [65238, 203],
                [65239, 161],
                [65240, 155]
            ]
        },
        "cycles": [
            [65238, 203, "read"],
            [65239, 161, "read"]
        ]
    },
    {
        "name": "cb d2 eb",
        "initial": {
            "pc": 16344,
            "s": 185,
            "a": 248,
            "x": 89,
            "y": 178,
            "p": 235,
            "ram": [
                [16344, 203],
                [16345, 210],
                [16346, 235]
            ]
        },
        "final": {
            "pc": 16346,
            "s": 185,
            "a": 248,
            "x": 134,
            "y": 178,
            "p": 232,
            "ram": [
                [16344, 203],
                [16345, 210],
                [16346, 235]
            ]
        },
        "cycles": [
            [16344, 203, "read"],
            [16345, 210, "read"]
        ]
    },
    {
        "name": "cb b8 35",
        "initial": {
            "pc": 34629,
            "s": 45,
            "a": 111,
            "x": 85,
            "y": 110,
            "p": 168,
            "ram": [
                [34629, 203],
                [34630, 184],
                [34631, 53]
            ]
        },
        "final": {
            "pc": 34631,
            "s": 45,
            "a": 111,
            "x": 141,
            "y": 110,
            "p": 168,
            "ram": [
                [34629, 203],
                [34630, 184],
                [34631, 53]
            ]
        },
        "cycles": [
            [34629, 203, "read"],
            [34630, 184, "read"]
        ]
    },
    {
        "name": "cb 64 ec",
        "initial": {
            "pc": 26852,
            "s": 65,
            "a": 74,
            "x": 11,
            "y": 238,
            "p": 224,
            "ram": [
                [26852, 203],
                [26853, 100],
                [26854, 236]
            ]
        },
        "final": {
            "pc": 26854,
            "s": 65,
            "a": 74,
            "x": 166,
            "y": 238,
            "p": 224,
            "ram": [
                [26852, 203],
                [26853, 100],
                [26854, 236]
            ]
        },
        "cycles": [
            [26852, 203, "read"],
            [26853, 100, "read"]
        ]
    },
    {
        "name": "cb 9f 24",
        "initial": {
            "pc": 41827,
            "s": 118,
            "a": 128,
            "x": 182,
            "y": 123,
            "p": 224,
            "ram": [
                [41827, 203],
                [41828, 159],
                [41829, 36]
            ]
        },
        "final": {
            "pc": 41829,
            "s": 118,
            "a": 128,
            "x": 225,
            "y": 123,
            "p": 224,
            "ram": [
                [41827, 203],
                [41828, 159],
                [41829, 36]
            ]
        },
        "cycles": [
            [41827, 203, "read"],
            [41828, 159, "read"]
        ]
    },
    {
        "name": "cb 51 e1",
        "initial": {
            "pc": 54645,
            "s": 206,
            "a": 198,
            "x": 175,
            "y": 50,
            "p": 38,
            "ram": [
                [54645, 203],
                [54646, 81],
                [54647, 225]
            ]
        },
        "final": {
            "pc": 54647,
            "s": 206,
            "a": 198,
            "x": 53,
            "y": 50,
            "p": 37,
            "ram": [
                [54645, 203],
                [54646, 81],
                [54647, 225]
            ]
        },
        "cycles": [
            [54645, 203, "read"],
            [54646, 81, "read"]
        ]
    },
    {
        "name": "cb 6f ac",
        "initial": {
            "pc": 25219,
            "s": 125,
            "a": 239,
            "x": 180,
            "y": 118,
            "p": 110,
            "ram": [
                [25219, 203],
                [25220, 111],
                [25221, 172]
            ]
        },
        "final": {
            "pc": 25221,
            "s": 125,
            "a": 239,
            "x": 53,
            "y": 118,
            "p": 109,
            "ram": [
                [25219, 203],
                [25220, 111],
                [25221, 172]
            ]
        },
        "cycles": [
            [25219, 203, "read"],
            [25220, 111, "read"]
        ]
    },
    {
        "name": "cb df bc",
        "initial": {
            "pc": 46994,
            "s": 1,
            "a": 217,
            "x": 232,
            "y": 125,
            "p": 36,
            "ram": [
                [46994, 203],
                [46995, 223],
                [46996, 188]
            ]
        },
        "final": {
            "pc": 46996,
            "s": 1,
            "a": 217,
            "x": 233,
            "y": 125,
            "p": 164,
            "ram": [
                [46994, 203],
                [46995, 223],
                [46996, 188]
            ]
        },
        "cycles": [
            [46994, 203, "read"],
            [46995, 223, "read"]
        ]
    },
    {
        "name": "cb 8d 4c",
        "initial": {
            "pc": 18949,
            "s": 203,
            "a": 205,
            "x": 228,
            "y": 174,
            "p": 104,
            "ram": [
                [18949, 203],
                [18950, 141],
                [18951, 76]
            ]
        },
        "final": {
            "pc": 18951,
            "s": 203,
            "a": 205,
            "x": 55,
            "y": 174,
            "p": 105,
            "ram": [
                [18949, 203],
                [18950, 141],
                [18951, 76]
            ]
        },
        "cycles": [
            [18949, 203, "read"],
            [18950, 141, "read"]
        ]
    },
    {
        "name": "cb c3 0a",
        "initial": {
            "pc": 53194,
            "s": 56,
            "a": 155,
            "x": 237,
            "y": 201,
            "p": 173,
            "ram": [
                [53194, 203],
                [53195, 195],
                [53196, 10]
            ]
        },
        "final": {
            "pc": 53196,
            "s": 56,
            "a": 155,
            "x": 198,
            "y": 201,
            "p": 172,
            "ram": [
                [53194, 203],
                [53195, 195],
                [53196, 10]
            ]
        },
        "cycles": [
            [53194, 203, "read"],
            [53195, 195, "read"]
        ]
    },
    {
        "name": "cb 53 a9",
        "initial": {
            "pc": 4518,
            "s": 160,
            "a": 252,
            "x": 178,
            "y": 206,
            "p": 237,
            "ram": [
                [4518, 203],
                [4519, 83],
                [4520, 169]
            ]
        },
        "final": {
            "pc": 4520,
            "s": 160,
            "a": 252,
            "x": 93,
            "y": 206,
            "p": 109,
            "ram": [
                [4518, 203],
                [4519, 83],
                [4520, 169]
            ]
        },
        "cycles": [
            [4518, 203, "read"],
            [4519, 83, "read"]
        ]
    },
    {
        "name": "cb 50 12",
        "initial": {
            "pc": 56822,
            "s": 136,
            "a": 21,
            "x": 255,
            "y": 255,
            "p": 43,
            "ram": [
                [56822, 203],
                [56823, 80],
                [56824, 18]
            ]
        },
        "final": {
            "pc": 56824,
            "s": 136,
            "a": 21,
            "x": 197,
            "y": 255,
            "p": 168,
            "ram": [
                [56822, 203],
                [56823, 80],
                [56824, 18]
            ]
        },
        "cycles": [
            [56822, 203, "read"],
            [56823, 80, "read"]
        ]
    },
    {
        "name": "cb aa 0c",
        "initial": {
            "pc": 11445,
            "s": 24,
            "a": 217,
            "x": 239,
            "y": 154,
            "p": 99,
            "ram": [
                [11445, 203],
                [11446, 170],
                [11447, 12]
            ]
        },
        "final": {
            "pc": 11447,
            "s": 24,
            "a": 217,
            "x": 31,
            "y": 154,
            "p": 97,
            "ram": [
                [11445, 203],
                [11446, 170],
                [11447, 12]
            ]
        },
        "cycles": [
            [11445, 203, "read"],
            [11446, 170, "read"]
        ]
    },
    {
        "name": "cb 89 71",
        "initial": {
            "pc": 33342,
            "s": 184,
            "a": 75,
            "x": 166,
            "y": 246,
            "p": 234,
            "ram": [
                [33342, 203],
                [33343, 137],
                [33344, 113]
            ]
        },
        "final": {
            "pc": 33344,
            "s": 184,
            "a": 75,
            "x": 121,
            "y": 246,
            "p": 104,
            "ram": [
                [33342, 203],
                [33343, 137],
                [33344, 113]
            ]
        },
        "cycles": [
            [33342, 203, "read"],
            [33343, 137, "read"]
        ]
    },
    {
        "name": "cb b7 e0",
        "initial": {
            "pc": 31278,
            "s": 34,
            "a": 251,
            "x": 66,
            "y": 244,
            "p": 174,
            "ram": [
                [31278, 203],
                [31279, 183],
                [31280, 224]
            ]
        },
        "final": {
            "pc": 31280,
            "s": 34,
            "a": 251,
            "x": 139,
            "y": 244,
            "p": 172,
            "ram": [
                [31278, 203],
                [31279, 183],
                [31280, 224]
            ]
        },
        "cycles": [
            [31278, 203, "read"],
            [31279, 183, "read"]
        ]
    },
    {
        "name": "cb a3 df",
        "initial": {
            "pc": 40504,
            "s": 60,
            "a": 50,
            "x": 205,
            "y": 96,
            "p": 39,
            "ram": [
                [40504, 203],
                [40505, 163],
                [40506, 223]
            ]
        },
        "final": {
            "pc": 40506,
            "s": 60,
            "a": 50,
            "x": 93,
            "y": 96,
            "p": 36,
            "ram": [
                [40504, 203],
                [40505, 163],
                [40506, 223]
            ]
        },
        "cycles": [
            [40504, 203, "read"],
            [40505, 163, "read"]
        ]
    },
    {
        "name": "cb 26 55",
        "initial": {
            "pc": 9093,
            "s": 144,
            "a": 162,
            "x": 26,
            "y": 211,
            "p": 33,
            "ram": [
                [9093, 203],
                [9094, 38],
                [9095, 85]
            ]
        },
        "final": {
            "pc": 9095,
            "s": 144,
            "a": 162,
            "x": 220,
            "y": 211,
            "p": 160,
            "ram": [
                [9093, 203],
                [9094, 38],
                [9095, 85]
            ]
        },
        "cycles": [
            [9093, 203, "read"],
            [9094, 38, "read"]
        ]
    },
    {
        "name": "cb d1 9c",
        "initial": {
            "pc": 21583,
            "s": 89,
            "a": 56,
            "x": 159,
            "y": 134,
            "p": 236,
            "ram": [
                [21583, 203],
                [21584, 209],
                [21585, 156]
            ]
        },
        "final": {
            "pc": 21585,
            "s": 89,
            "a": 56,
            "x": 71,
            "y": 134,
            "p": 108,
            "ram": [
                [21583, 203],
                [21584, 209],
                [21585, 156]
            ]
        },
        "cycles": [
            [21583, 203, "read"],
            [21584, 209, "read"]
        ]
    },
    {
        "name": "cb b1 d3",
        "initial": {
            "pc": 41727,
            "s": 216,
            "a": 78,
            "x": 23,
            "y": 173,
            "p": 164,
            "ram": [
                [41727, 203],
                [41728, 177],
                [41729, 211]
            ]
        },
        "final": {
            "pc": 41729,
            "s": 216,
            "a": 78,
            "x": 85,
            "y": 173,
            "p": 36,
            "ram": [
                [41727, 203],
                [41728, 177],
                [41729, 211]
            ]
        },
        "cycles": [
            [41727, 203, "read"],
            [41728, 177, "read"]
        ]
    },
    {
        "name": "cb ba 46",
        "initial": {
            "pc": 17873,
            "s": 165,
            "a": 255,
            "x": 15,
            "y": 205,
            "p": 47,
            "ram": [
                [17873, 203],
                [17874, 186],
                [17875, 70]
            ]
        },
        "final": {
            "pc": 17875,
            "s": 165,
            "a": 255,
            "x": 85,
            "y": 205,
            "p": 44,
            "ram": [
                [17873, 203],
                [17874, 186],
                [17875, 70]
            ]
        },
        "cycles": [
            [17873, 203, "read"],
            [17874, 186, "read"]
        ]
    },
    {
        "name": "cb 22 c4",
        "initial": {
            "pc": 58760,
            "s": 73,
            "a": 153,
            "x": 224,
            "y": 141,
            "p": 237,
            "ram": [
                [58760, 203],
                [58761, 34],
                [58762, 196]
            ]
        },
        "final": {
            "pc": 58762,
            "s": 73,
            "a": 153,
            "x": 94,
            "y": 141,
            "p": 109,
            "ram": [
                [58760, 203],
                [58761, 34],
                [58762, 196]
            ]
        },
        "cycles": [
            [58760, 203, "read"],
            [58761, 34, "read"]
        ]
    },
    {
        "name": "cb f2 79",
        "initial": {
            "pc": 282,
            "s": 92,
            "a": 204,
            "x": 159,
            "y": 214,
            "p": 100,
            "ram": [
                [282, 203],
                [283, 242],
                [284, 121]
            ]
        },
        "final": {
            "pc": 284,
            "s": 92,
            "a": 204,
            "x": 154,
            "y": 214,
            "p": 228,
            "ram": [
                [282, 203],
                [283, 242],
                [284, 121]
            ]
        },
        "cycles": [
            [282, 203, "read"],
            [283, 242, "read"]
        ]
    },
    {
        "name": "cb bd 7b",
        "initial": {
            "pc": 45129,
            "s": 62,
            "a": 150,
            "x": 240,
            "y": 22,
            "p": 228,
            "ram": [
                [45129, 203],
                [45130, 189],
                [45131, 123]
            ]
        },
        "final": {
            "pc": 45131,
            "s": 62,
            "a": 150,
            "x": 211,
            "y": 22,
            "p": 228,
            "ram": [
                [45129, 203],
                [45130, 189],
                [45131, 123]
            ]
        },
        "cycles": [
            [45129, 203, "read"],
            [45130, 189, "read"]
        ]
    },
    {
        "name": "cb 05 87",
        "initial": {
            "pc": 24513,
            "s": 158,
            "a": 172,
            "x": 99,
            "y": 154,
            "p": 167,
            "ram": [
                [24513, 203],
                [24514, 5],
                [24515, 135]
            ]
        },
        "final": {
            "pc": 24515,
            "s": 158,
            "a": 172,
            "x": 27,
            "y": 154,
            "p": 37,
            "ram": [
                [24513, 203],
                [24514, 5],
                [24515, 135]
            ]
        },
        "cycles": [
            [24513, 203, "read"],
            [24514, 5, "read"]
        ]
    },
    {
        "name": "cb d4 88",
        "initial": {
            "pc": 37224,
            "s": 165,
            "a": 187,
            "x": 144,
            "y": 111,
            "p": 170,
            "ram": [
                [37224, 203],
                [37225, 212],
                [37226, 136]
            ]
        },
        "final": {
            "pc": 37226,
            "s": 165,
            "a": 187,
            "x": 188,
            "y": 111,
            "p": 168,
            "ram": [
                [37224, 203],
                [37225, 212],
                [37226, 136]
            ]
        },
        "cycles": [
            [37224, 203, "read"],
            [37225, 212, "read"]
        ]
    },
    {
        "name": "cb 3c e7",
        "initial": {
            "pc": 63887,
            "s": 232,
            "a": 106,
            "x": 50,
            "y": 150,
            "p": 34,
            "ram": [
                [63887, 203],
                [63888, 60],
                [63889, 231]
            ]
        },
        "final": {
            "pc": 63889,
            "s": 232,
            "a": 106,
            "x": 230,
            "y": 150,
            "p": 160,
            "ram": [
                [63887, 203],
                [63888, 60],
                [63889, 231]
            ]
        },
        "cycles": [
            [63887, 203, "read"],
            [63888, 60, "read"]
        ]
    },
    {
        "name": "cb 1d c8",
        "initial": {
            "pc": 24997,
            "s": 43,
            "a": 93,
            "x": 253,
            "y": 151,
            "p": 169,
            "ram": [
                [24997, 203],
                [24998, 29],
                [24999, 200]
            ]
        },
        "final": {
            "pc": 24999,
            "s": 43,
            "a": 93,
            "x": 64,
            "y": 151,
            "p": 41,
            "ram": [
                [24997, 203],
                [24998, 29],
                [24999, 200]
            ]
        },
        "cycles": [
            [24997, 203, "read"],
            [24998, 29, "read"]
        ]
    },
    {
        "name": "cb 56 4a",
        "initial": {
            "pc": 30926,
            "s": 27,
            "a": 9,
            "x": 250,
            "y": 84,
            "p": 32,
            "ram": [
                [30926, 203],
                [30927, 86],
                [30928, 74]
            ]
        },
        "final": {
            "pc": 30928,
            "s": 27,
            "a": 9,
            "x": 178,
            "y": 84,
            "p": 160,
            "ram": [
                [30926, 203],
                [30927, 86],
                [30928, 74]
            ]
        },
        "cycles": [
            [30926, 203, "read"],
            [30927, 86, "read"]
        ]
    },
    {
        "name": "cb 31 02",
        "initial": {
            "pc": 20461,
            "s": 86,
            "a": 164,
            "x": 255,
            "y": 174,
            "p": 225,
            "ram": [
                [20461, 203],
                [20462, 49],
                [20463, 2]
            ]
        },
        "final": {
            "pc": 20463,
            "s": 86,
            "a": 164,
            "x": 115,
            "y": 174,
            "p": 97,
            "ram": [
                [20461, 203],
                [20462, 49],
                [20463, 2]
            ]
        },
        "cycles": [
            [20461, 203, "read"],
            [20462, 49, "read"]
        ]
    },
    {
        "name": "cb 0b 5f",
        "initial": {
            "pc": 37276,
            "s": 84,
            "a": 183,
            "x": 1,
            "y": 108,
            "p": 224,
            "ram": [
                [37276, 203],
                [37277, 11],
                [37278, 95]
            ]
        },
        "final": {
            "pc": 37278,
            "s": 84,
            "a": 183,
            "x": 246,
            "y": 108,
            "p": 224,
            "ram": [
                [37276, 203],
                [37277, 11],
                [37278, 95]
            ]
        },
        "cycles": [
            [37276, 203, "read"],
            [37277, 11, "read"]
        ]
    },
    {
        "name": "cb 28 53",
        "initial": {
            "pc": 12502,
            "s": 46,
            "a": 197,
            "x": 16,
            "y": 107,
            "p": 96,
            "ram": [
                [12502, 203],
                [12503, 40],
                [12504, 83]
            ]
        },
        "final": {
            "pc": 12504,
            "s": 46,
            "a": 197,
            "x": 216,
            "y": 107,
            "p": 224,
            "ram": [
                [12502, 203],
                [12503, 40],
                [12504, 83]
            ]
        },
        "cycles": [
            [12502, 203, "read"],
            [12503, 40, "read"]
        ]
    },
    {
        "name": "cb f7 7c",
        "initial": {
            "pc": 49037,
            "s": 138,
            "a": 222,
            "x": 237,
            "y": 6,
            "p": 36,
            "ram": [
                [49037, 203],
                [49038, 247],
                [49039, 124]
            ]
        },
        "final": {
            "pc": 49039,
            "s": 138,
            "a": 222,
            "x": 213,
            "y": 6,
            "p": 164,
            "ram": [
                [49037, 203],
                [49038, 247],
                [49039, 124]
            ]
        },
        "cycles": [
            [49037, 203, "read"],
            [49038, 247, "read"]
        ]
    },
    {
        "name": "cb 5f 0f",
        "initial": {
            "pc": 64769,
            "s": 17,
            "a": 206,
            "x": 249,
            "y": 114,
            "p": 98,
            "ram": [
                [64769, 203],
                [64770, 95],
                [64771, 15]
            ]
        },
        "final": {
            "pc": 64771,
            "s": 17,
            "a": 206,
            "x": 105,
            "y": 114,
            "p": 97,
            "ram": [
                [64769, 203],
                [64770, 95],
                [64771, 15]
            ]
        },
        "cycles": [
            [64769, 203, "read"],
            [64770, 95, "read"]
        ]
    },
    {
        "name": "cb 19 2b",
        "initial": {
            "pc": 44621,
            "s": 196,
            "a": 21,
            "x": 114,
            "y": 33,
            "p": 173,
            "ram": [
                [44621, 203],
                [44622, 25],
                [44623, 43]
            ]
        },
        "final": {
            "pc": 44623,
            "s": 196,
            "a": 21,
            "x": 247,
            "y": 33,
            "p": 172,
            "ram": [
                [44621, 203],
                [44622, 25],
                [44623, 43]
            ]
        },
        "cycles": [
            [44621, 203, "read"],
            [44622, 25, "read"]
        ]
    },
    {
        "name": "cb 18 c4",
        "initial": {
            "pc": 46942,
            "s": 44,
            "a": 132,
            "x": 75,
            "y": 96,
            "p": 42,
            "ram": [
                [46942, 203],
                [46943, 24],
                [46944, 196]
            ]
        },
        "final": {
            "pc": 46944,
            "s": 44,
            "a": 132,
            "x": 232,
            "y": 96,
            "p": 168,
            "ram": [
                [46942, 203],
                [46943, 24],
                [46944, 196]
            ]
        },
        "cycles": [
            [46942, 203, "read"],
            [46943, 24, "read"]
        ]
    },
    {
        "name": "cb 6d 13",
        "initial": {
            "pc": 5401,
            "s": 6,
            "a": 8,
            "x": 115,
            "y": 120,
            "p": 162,
            "ram": [
                [5401, 203],
                [5402, 109],
                [5403, 19]
            ]
        },
        "final": {
            "pc": 5403,
            "s": 6,
            "a": 8,
            "x": 147,
            "y": 120,
            "p": 160,
            "ram": [
                [5401, 203],
                [5402, 109],
                [5403, 19]
            ]
        },
        "cycles": [
            [5401, 203, "read"],
            [5402, 109, "read"]
        ]
    },
    {
        "name": "cb a0 97",
        "initial": {
            "pc": 11123,
            "s": 135,
            "a": 38,
            "x": 22,
            "y": 223,
            "p": 232,
            "ram": [
                [11123, 203],
                [11124, 160],
                [11125, 151]
            ]
        },
        "final": {
            "pc": 11125,
            "s": 135,
            "a": 38,
            "x": 102,
            "y": 223,
            "p": 104,
            "ram": [
                [11123, 203],
                [11124, 160],
                [11125, 151]
            ]
        },
        "cycles": [
            [11123, 203, "read"],
            [11124, 160, "read"]
        ]
    },
    {
        "name": "cb fc 62",
        "initial": {
            "pc": 2329,
            "s": 133,
            "a": 189,
            "x": 36,
            "y": 20,
            "p": 162,
            "ram": [
                [2329, 203],
                [2330, 252],
                [2331, 98]
            ]
        },
        "final": {
            "pc": 2331,
            "s": 133,
            "a": 189,
            "x": 40,
            "y": 20,
            "p": 32,
            "ram": [
                [2329, 203],
                [2330, 252],
                [2331, 98]
            ]
        },
        "cycles": [
            [2329, 203, "read"],
            [2330, 252, "read"]
        ]
    },
    {
        "name": "cb 9e 65",
        "initial": {
            "pc": 36867,
            "s": 99,
            "a": 55,
            "x": 250,
            "y": 63,
            "p": 174,
            "ram": [
                [36867, 203],
                [36868, 158],
                [36869, 101]
            ]
        },
        "final": {
            "pc": 36869,
            "s": 99,
            "a": 55,
            "x": 148,
            "y": 63,
            "p": 172,
            "ram": [
                [36867, 203],
                [36868, 158],
                [36869, 101]
            ]
        },
        "cycles": [
            [36867, 203, "read"],
            [36868, 158, "read"]
        ]
    },
    {
        "name": "cb 1b 7b",
        "initial": {
            "pc": 38017,
            "s": 104,
            "a": 105,
            "x": 14,
            "y": 234,
            "p": 44,
            "ram": [
                [38017, 203],
                [38018, 27],
                [38019, 123]
            ]
        },
        "final": {
            "pc": 38019,
            "s": 104,
            "a": 105,
            "x": 237,
            "y": 234,
            "p": 172,
            "ram": [
                [38017, 203],
                [38018, 27],
                [38019, 123]
            ]
        },
        "cycles": [
            [38017, 203, "read"],
            [38018, 27, "read"]
        ]
    },
    {
        "name": "cb d6 0a",
        "initial": {
            "pc": 38014,
            "s": 110,
            "a": 2,
            "x": 42,
            "y": 18,
            "p": 236,
            "ram": [
                [38014, 203],
                [38015, 214],
                [38016, 10]
            ]
        },
        "final": {
            "pc": 38016,
            "s": 110,
            "a": 2,
            "x": 44,
            "y": 18,
            "p": 108,
            "ram": [
                [38014, 203],
                [38015, 214],
                [38016, 10]
            ]
        },
        "cycles": [
            [38014, 203, "read"],
            [38015, 214, "read"]
        ]
    },
    {
        "name": "cb 47 2e",
        "initial": {
            "pc": 28312,
            "s": 35,
            "a": 71,
            "x": 38,
            "y": 95,
            "p": 101,
            "ram": [
                [28312, 203],
                [28313, 71],
                [28314, 46]
            ]
        },
        "final": {
            "pc": 28314,
            "s": 35,
            "a": 71,
            "x": 191,
            "y": 95,
            "p": 228,
            "ram": [
                [28312, 203],
                [28313, 71],
                [28314, 46]
            ]
        },
        "cycles": [
            [28312, 203, "read"],
            [28313, 71, "read"]
        ]
    },
    {
        "name": "cb a5 7a",
        "initial": {
            "pc": 57229,
            "s": 29,
            "a": 46,
            "x": 142,
            "y": 202,
            "p": 104,
            "ram": [
                [57229, 203],
                [57230, 165],
                [57231, 122]
            ]
        },
        "final": {
            "pc": 57231,
            "s": 29,
            "a": 46,
            "x": 105,
            "y": 202,
            "p": 104,
            "ram": [
                [57229, 203],
                [57230, 165],
                [57231, 122]
            ]
        },
        "cycles": [
            [57229, 203, "read"],
            [57230, 165, "read"]
        ]
    },
    {
        "name": "cb 32 29",
        "initial": {
            "pc": 53056,
            "s": 222,
            "a": 193,
            "x": 83,
            "y": 68,
            "p": 45,
            "ram": [
                [53056, 203],
                [53057, 50],
                [53058, 41]
            ]
        },
        "final": {
            "pc": 53058,
            "s": 222,
            "a": 193,
            "x": 15,
            "y": 68,
            "p": 45,
            "ram": [
                [53056, 203],
                [53057, 50],
                [53058, 41]
            ]
        },
        "cycles": [
            [53056, 203, "read"],
            [53057, 50, "read"]
        ]
    },
    {
        "name": "cb 1e e0",
        "initial": {
            "pc": 4365,
            "s": 53,
            "a": 181,
            "x": 36,
            "y": 21,
            "p": 239,
            "ram": [
                [4365, 203],
                [4366, 30],
                [4367, 224]
            ]
        },
        "final": {
            "pc": 4367,
            "s": 53,
            "a": 181,
            "x": 6,
            "y": 21,
            "p": 109,
            "ram": [
                [4365, 203],
                [4366, 30],
                [4367, 224]
            ]
        },
        "cycles": [
            [4365, 203, "read"],
            [4366, 30, "read"]
        ]
    },
    {
        "name": "cb 30 94",
        "initial": {
            "pc": 51338,
            "s": 4,
            "a": 145,
            "x": 157,
            "y": 66,
            "p": 169,
            "ram": [
                [51338, 203],
                [51339, 48],
                [51340, 148]
            ]
        },
        "final": {
            "pc": 51340,
            "s": 4,
            "a": 145,
            "x": 97,
            "y": 66,
            "p": 41,
            "ram": [
                [51338, 203],
                [51339, 48],
                [51340, 148]
            ]
        },
        "cycles": [
            [51338, 203, "read"],
            [51339, 48, "read"]
        ]
    },
    {
        "name": "cb d6 3b",
        "initial": {
            "pc": 14581,
            "s": 2,
            "a": 220,
            "x": 231,
            "y": 84,
            "p": 225,
            "ram": [
                [14581, 203],
                [14582, 214],
                [14583, 59]
            ]
        },
        "final": {
            "pc": 14583,
            "s": 2,
            "a": 220,
            "x": 238,
            "y": 84,
            "p": 224,
            "ram": [
                [14581, 203],
                [14582, 214],
                [14583, 59]
            ]
        },
        "cycles": [
            [14581, 203, "read"],
            [14582, 214, "read"]
        ]
    },
    {
        "name": "cb 5f ce",
        "initial": {
            "pc": 52270,
            "s": 247,
            "a": 168,
            "x": 3,
            "y": 39,
            "p": 32,
            "ram": [
                [52270, 203],
                [52271, 95],
                [52272, 206]
            ]
        },
        "final": {
            "pc": 52272,
            "s": 247,
            "a": 168,
            "x": 161,
            "y": 39,
            "p": 160,
            "ram": [
                [52270, 203],
                [52271, 95],
                [52272, 206]
            ]
        },
        "cycles": [
            [52270, 203, "read"],
            [52271, 95, "read"]
        ]
    },
    {
        "name": "cb 7c 71",
        "initial": {
            "pc": 15908,
            "s": 27,
            "a": 53,
            "x": 70,
            "y": 72,
            "p": 39,
            "ram": [
                [15908, 203],
                [15909, 124],
                [15910, 113]
            ]
        },
        "final": {
            "pc": 15910,
            "s": 27,
            "a": 53,
            "x": 136,
            "y": 72,
            "p": 164,
            "ram": [
                [15908, 203],
                [15909, 124],
                [15910, 113]
            ]
        },
        "cycles": [
            [15908, 203, "read"],
            [15909, 124, "read"]
        ]
    },
    {
        "name": "cb 21 d9",
        "initial": {
            "pc": 14894,
            "s": 174,
            "a": 122,
            "x": 227,
            "y": 128,
            "p": 226,
            "ram": [
                [14894, 203],
                [14895, 33],
                [14896, 217]
            ]
        },
        "final": {
            "pc": 14896,
            "s": 174,
            "a": 122,
            "x": 65,
            "y": 128,
            "p": 97,
            "ram": [
                [14894, 203],
                [14895, 33],
                [14896, 217]
            ]
        },
        "cycles": [
            [14894, 203, "read"],
            [14895, 33, "read"]
        ]
    },
    {
        "name": "cb ff e7",
        "initial": {
            "pc": 4048,
            "s": 134,
            "a": 38,
            "x": 193,
            "y": 68,
            "p": 160,
            "ram": [
                [4048, 203],
                [4049, 255],
                [4050, 231]
            ]
        },
        "final": {
            "pc": 4050,
            "s": 134,
            "a": 38,
            "x": 1,
            "y": 68,
            "p": 32,
            "ram": [
                [4048, 203],
                [4049, 255],
                [4050, 231]
            ]
        },
        "cycles": [
            [4048, 203, "read"],
            [4049, 255, "read"]
        ]
    },
    {
        "name": "cb 77 35",
        "initial": {
            "pc": 36515,
            "s": 51,
            "a": 139,
            "x": 12,
            "y": 245,
            "p": 108,
            "ram": [
                [36515, 203],
                [36516, 119],
                [36517, 53]
            ]
        },
        "final": {
            "pc": 36517,
            "s": 51,
            "a": 139,
            "x": 145,
            "y": 245,
            "p": 236,
            "ram": [
                [36515, 203],
                [36516, 119],
                [36517, 53]
            ]
        },
        "cycles": [
            [36515, 203, "read"],
            [36516, 119, "read"]
        ]
    },
    {
        "name": "cb 8a 79",
        "initial": {
            "pc": 36344,
            "s": 49,
            "a": 115,
            "x": 14,
            "y": 62,
            "p": 166,
            "ram": [
                [36344, 203],
                [36345, 138],
                [36346, 121]
            ]
        },
        "final": {
            "pc": 36346,
            "s": 49,
            "a": 115,
            "x": 120,
            "y": 62,
            "p": 36,
            "ram": [
                [36344, 203],
                [36345, 138],
                [36346, 121]
            ]
        },
        "cycles": [
            [36344, 203, "read"],
            [36345, 138, "read"]
        ]
    },
    {
        "name": "cb 21 43",
        "initial": {
            "pc": 51039,
            "s": 169,
            "a": 119,
            "x": 184,
            "y": 32,
            "p": 228,
            "ram": [
                [51039, 203],
                [51040, 33],
                [51041, 67]
            ]
        },
        "final": {
            "pc": 51041,
            "s": 169,
            "a": 119,
            "x": 15,
            "y": 32,
            "p": 101,
            "ram": [
                [51039, 203],
                [51040, 33],
                [51041, 67]
            ]
        },
        "cycles": [
            [51039, 203, "read"],
            [51040, 33, "read"]
        ]
    },
    {
        "name": "cb 66 4f",
        "initial": {
            "pc": 47705,
            "s": 252,
            "a": 237,
            "x": 85,
            "y": 52,
            "p": 224,
            "ram": [
                [47705, 203],
                [47706, 102],
                [47707, 79]
            ]
        },
        "final": {
            "pc": 47707,
            "s": 252,
            "a": 237,
            "x": 223,
            "y": 52,
            "p": 224,
            "ram": [
                [47705, 203],
                [47706, 102],
                [47707, 79]
            ]
        },
        "cycles": [
            [47705, 203, "read"],
            [47706, 102, "read"]
        ]
    },
    {
        "name": "cb 69 8f",
        "initial": {
            "pc": 49906,
            "s": 131,
            "a": 152,
            "x": 101,
            "y": 152,
            "p": 44,
            "ram": [
                [49906, 203],
                [49907, 105],
                [49908, 143]
            ]
        },
        "final": {
            "pc": 49908,
            "s": 131,
            "a": 152,
            "x": 151,
            "y": 152,
            "p": 172,
            "ram": [
                [49906, 203],
                [49907, 105],
                [49908, 143]
            ]
        },
        "cycles": [
            [49906, 203, "read"],
            [49907, 105, "read"]
        ]
    },
    {
        "name": "cb a7 7f",
        "initial": {
            "pc": 39278,
            "s": 51,
            "a": 22,
            "x": 209,
            "y": 240,
            "p": 33,
            "ram": [
                [39278, 203],
                [39279, 167],
                [39280, 127]
            ]
        },
        "final": {
            "pc": 39280,
            "s": 51,
            "a": 22,
            "x": 105,
            "y": 240,
            "p": 32,
            "ram": [
                [39278, 203],
                [39279, 167],
                [39280, 127]
            ]
        },
        "cycles": [
            [39278, 203, "read"],
            [39279, 167, "read"]
        ]
    },
    {
        "name": "cb 2a 67",
        "initial": {
            "pc": 64019,
            "s": 17,
            "a": 80,
            "x": 44,
            "y": 19,
            "p": 99,
            "ram": [
                [64019, 203],
                [64020, 42],
                [64021, 103]
            ]
        },
        "final": {
            "pc": 64021,
            "s": 17,
            "a": 80,
            "x": 214,
            "y": 19,
            "p": 224,
            "ram": [
                [64019, 203],
                [64020, 42],
                [64021, 103]
            ]
        },
        "cycles": [
            [64019, 203, "read"],
            [64020, 42, "read"]
        ]
    },
    {
        "name": "cb ae 8c",
        "initial": {
            "pc": 11130,
            "s": 89,
            "a": 5,
            "x": 61,
            "y": 252,
            "p": 236,
            "ram": [
                [11130, 203],
                [11131, 174],
                [11132, 140]
            ]
        },
        "final": {
            "pc": 11132,
            "s": 89,
            "a": 5,
            "x": 87,
            "y": 252,
            "p": 108,
            "ram": [
                [11130, 203],
                [11131, 174],
                [11132, 140]
            ]
        },
        "cycles": [
            [11130, 203, "read"],
            [11131, 174, "read"]
        ]
    },
    {
        "name": "cb ab cc",
        "initial": {
            "pc": 44606,
            "s": 216,
            "a": 14,
            "x": 123,
            "y": 181,
            "p": 46,
            "ram": [
                [44606, 203],
                [44607, 171],
                [44608, 204]
            ]
        },
        "final": {
            "pc": 44608,
            "s": 216,
            "a": 14,
            "x": 95,
            "y": 181,
            "p": 44,
            "ram": [
                [44606, 203],
                [44607, 171],
                [44608, 204]
            ]
        },
        "cycles": [
            [44606, 203, "read"],
            [44607, 171, "read"]
        ]
    },
    {
        "name": "cb fa 3a",
        "initial": {
            "pc": 14509,
            "s": 57,
            "a": 237,
            "x": 238,
            "y": 250,
            "p": 224,
            "ram": [
                [14509, 203],
                [14510, 250],
                [14511, 58]
            ]
        },
        "final": {
            "pc": 14511,
            "s": 57,
            "a": 237,
            "x": 242,
            "y": 250,
            "p": 224,
            "ram": [
                [14509, 203],
                [14510, 250],
                [14511, 58]
            ]
        },
        "cycles": [
            [14509, 203, "read"],
            [14510, 250, "read"]
        ]
    },
    {
        "name": "cb 62 23",
        "initial": {
            "pc": 2343,
            "s": 66,
            "a": 85,
            "x": 182,
            "y": 249,
            "p": 172,
            "ram": [
                [2343, 203],
                [2344, 98],
                [2345, 35]
            ]
        },
        "final": {
            "pc": 2345,
            "s": 66,
            "a": 85,
            "x": 178,
            "y": 249,
            "p": 172,
            "ram": [
                [2343, 203],
                [2344, 98],
                [2345, 35]
            ]
        },
        "cycles": [
            [2343, 203, "read"],
            [2344, 98, "read"]
        ]
    },
    {
        "name": "cb c7 cb",
        "initial": {
            "pc": 20411,
            "s": 13,
            "a": 182,
            "x": 107,
            "y": 3,
            "p": 99,
            "ram": [
                [20411, 203],
                [20412, 199],
                [20413, 203]
            ]
        },
        "final": {
            "pc": 20413,
            "s": 13,
            "a": 182,
            "x": 91,
            "y": 3,
            "p": 96,
            "ram": [
                [20411, 203],
                [20412, 199],
                [20413, 203]
            ]
        },
        "cycles": [
            [20411, 203, "read"],
            [20412, 199, "read"]
        ]
    },
    {
        "name": "cb 13 41",
        "initial": {
            "pc": 47680,
            "s": 106,
            "a": 34,
            "x": 139,
            "y": 137,
            "p": 33,
            "ram": [
                [47680, 203],
                [47681, 19],
                [47682, 65]
            ]
        },
        "final": {
            "pc": 47682,
            "s": 106,
            "a": 34,
            "x": 239,
            "y": 137,
            "p": 160,
            "ram": [
                [47680, 203],
                [47681, 19],
                [47682, 65]
            ]
        },
        "cycles": [
            [47680, 203, "read"],
            [47681, 19, "read"]
        ]
    },
    {
        "name": "cb 2d 66",
        "initial": {
            "pc": 39036,
            "s": 215,
            "a": 188,
            "x": 206,
            "y": 238,
            "p": 168,
            "ram": [
                [39036, 203],
                [39037, 45],
                [39038, 102]
            ]
        },
        "final": {
            "pc": 39038,
            "s": 215,
            "a": 188,
            "x": 95,
            "y": 238,
            "p": 41,
            "ram": [
                [39036, 203],
                [39037, 45],
                [39038, 102]
            ]
        },
        "cycles": [
            [39036, 203, "read"],
            [39037, 45, "read"]
        ]
    },
    {
        "name": "cb b4 0c",
        "initial": {
            "pc": 35289,
            "s": 150,
            "a": 138,
            "x": 41,
            "y": 8,
            "p": 229,
            "ram": [
                [35289, 203],
                [35290, 180],
                [35291, 12]
            ]
        },
        "final": {
            "pc": 35291,
            "s": 150,
            "a": 138,
            "x": 84,
            "y": 8,
            "p": 100,
            "ram": [
                [35289, 203],
                [35290, 180],
                [35291, 12]
            ]
        },
        "cycles": [
            [35289, 203, "read"],
            [35290, 180, "read"]
        ]
    }
]
